composio_anthropic/__init__.py
composio_anthropic/provider.py
composio_anthropic/py.typed
composio_anthropic-0.10.7.dist-info/METADATA
composio_anthropic-0.10.7.dist-info/WHEEL
composio_anthropic-0.10.7.dist-info/top_level.txt
composio_anthropic-0.10.7.dist-info/RECORD
